gradio_grid/__init__.py
gradio_grid/grid.py
gradio_grid/grid.pyi
gradio_grid/templates/component/index.js
gradio_grid/templates/component/style.css
gradio_grid-1.0.2.dist-info/METADATA
gradio_grid-1.0.2.dist-info/WHEEL
gradio_grid-1.0.2.dist-info/RECORD
