Metadata-Version: 2.3
Name: gradio_grid
Version: 1.0.2
Summary: Grid is a layout element within Blocks that renders all children in a two dimensional grid system.
Project-URL: Changelog, https://github.com/dwancin/gradio-grid/releases
Author: Daniel Ialcin Misser Westergaard
License-Expression: Apache-2.0
Keywords: gradio-custom-component,gradio-template-Row,grid,layout,two-dimensional
Classifier: Development Status :: 3 - Alpha
Classifier: Operating System :: OS Independent
Classifier: Programming Language :: Python :: 3
Classifier: Programming Language :: Python :: 3 :: Only
Classifier: Programming Language :: Python :: 3.8
Classifier: Programming Language :: Python :: 3.9
Classifier: Programming Language :: Python :: 3.10
Classifier: Programming Language :: Python :: 3.11
Classifier: Topic :: Scientific/Engineering
Classifier: Topic :: Scientific/Engineering :: Artificial Intelligence
Classifier: Topic :: Scientific/Engineering :: Visualization
Requires-Python: >=3.8
Requires-Dist: gradio<5.0,>=4.0
Provides-Extra: dev
Requires-Dist: build; extra == 'dev'
Requires-Dist: twine; extra == 'dev'
